dacite_ext/__init__.py
dacite_ext-0.1.3.dist-info/LICENSE
dacite_ext-0.1.3.dist-info/WHEEL
dacite_ext-0.1.3.dist-info/METADATA
dacite_ext-0.1.3.dist-info/RECORD
