Metadata-Version: 2.1
Name: dacite-ext
Version: 0.1.3
Summary: Dacite library extended
Home-page: https://github.com/rominf/dacite-ext
License: MIT
Author: Roman Inflianskas
Author-email: infroma@gmail.com
Requires-Python: >=3.6,<4.0
Classifier: License :: OSI Approved :: MIT License
Classifier: Programming Language :: Python :: 3
Classifier: Programming Language :: Python :: 3.6
Classifier: Programming Language :: Python :: 3.7
Requires-Dist: dacite
